picard/__init__.py
picard/album.py
picard/audit.py
picard/cluster.py
picard/collection.py
picard/config.py
picard/config_upgrade.py
picard/dataobj.py
picard/file.py
picard/i18n.py
picard/log.py
picard/mbjson.py
picard/metadata.py
picard/oauth.py
picard/plugin.py
picard/pluginmanager.py
picard/profile.py
picard/releasegroup.py
picard/resources.py
picard/similarity.py
picard/tagger.py
picard/track.py
picard/version.py
picard/acoustid/__init__.py
picard/acoustid/json_helpers.py
picard/acoustid/manager.py
picard/acoustid/recordings.py
picard/browser/__init__.py
picard/browser/addrelease.py
picard/browser/browser.py
picard/browser/filelookup.py
picard/const/__init__.py
picard/const/appdirs.py
picard/const/attributes.py
picard/const/countries.py
picard/const/languages.py
picard/const/locales.py
picard/const/scripts.py
picard/const/sys.py
picard/coverart/__init__.py
picard/coverart/image.py
picard/coverart/utils.py
picard/coverart/providers/__init__.py
picard/coverart/providers/caa.py
picard/coverart/providers/caa_release_group.py
picard/coverart/providers/local.py
picard/coverart/providers/provider.py
picard/coverart/providers/urlrels.py
picard/disc/__init__.py
picard/disc/dbpoweramplog.py
picard/disc/eaclog.py
picard/disc/utils.py
picard/disc/whipperlog.py
picard/formats/__init__.py
picard/formats/ac3.py
picard/formats/apev2.py
picard/formats/asf.py
picard/formats/id3.py
picard/formats/midi.py
picard/formats/mp4.py
picard/formats/util.py
picard/formats/vorbis.py
picard/formats/wav.py
picard/formats/mutagenext/__init__.py
picard/formats/mutagenext/aac.py
picard/formats/mutagenext/ac3.py
picard/formats/mutagenext/compatid3.py
picard/formats/mutagenext/tak.py
picard/plugins/__init__.py
picard/script/__init__.py
picard/script/functions.py
picard/script/parser.py
picard/script/serializer.py
picard/ui/__init__.py
picard/ui/aboutdialog.py
picard/ui/caa_types_selector.py
picard/ui/cdlookup.py
picard/ui/checkbox_list_item.py
picard/ui/collectionmenu.py
picard/ui/colors.py
picard-2.13.2.dist-info/AUTHORS.txt
picard-2.13.2.dist-info/COPYING.txt
picard-2.13.2.dist-info/METADATA
picard-2.13.2.dist-info/WHEEL
picard-2.13.2.dist-info/top_level.txt
picard-2.13.2.dist-info/RECORD
