Metadata-Version: 2.2
Name: picard
Version: 2.13.2
Summary: The next generation MusicBrainz tagger
Home-page: https://picard.musicbrainz.org/
Keywords: MusicBrainz metadata tagger picard
Classifier: License :: OSI Approved :: GNU General Public License v2 or later (GPLv2+)
Classifier: Development Status :: 5 - Production/Stable
Classifier: Environment :: MacOS X
Classifier: Environment :: Win32 (MS Windows)
Classifier: Environment :: X11 Applications :: Qt
Classifier: Programming Language :: Python :: 3
Classifier: Programming Language :: Python :: 3 :: Only
Classifier: Programming Language :: Python :: 3.8
Classifier: Programming Language :: Python :: 3.9
Classifier: Programming Language :: Python :: 3.10
Classifier: Programming Language :: Python :: 3.11
Classifier: Programming Language :: Python :: 3.12
Classifier: Programming Language :: Python :: 3.13
Classifier: Operating System :: MacOS
Classifier: Operating System :: Microsoft :: Windows
Classifier: Operating System :: POSIX :: Linux
Classifier: Topic :: Multimedia :: Sound/Audio
Classifier: Topic :: Multimedia :: Sound/Audio :: Analysis
Classifier: Intended Audience :: End Users/Desktop
Requires-Python: ~=3.8
License-File: COPYING.txt
License-File: AUTHORS.txt
Requires-Dist: discid~=1.0
Requires-Dist: fasteners~=0.14
Requires-Dist: Markdown~=3.2
Requires-Dist: mutagen~=1.37
Requires-Dist: PyJWT~=2.0
Requires-Dist: pyobjc-core<11,>=6.2; sys_platform == "darwin"
Requires-Dist: pyobjc-framework-Cocoa<11,>=6.2; sys_platform == "darwin"
Requires-Dist: PyQt5-sip<=12.15.0; python_version < "3.9"
Requires-Dist: PyQt5~=5.11
Requires-Dist: python-dateutil~=2.7
Requires-Dist: pywin32; sys_platform == "win32"
Requires-Dist: PyYAML<7,>=5.1
Requires-Dist: charset-normalizer~=3.3
Dynamic: classifier
Dynamic: description
Dynamic: description-content-type
Dynamic: home-page
Dynamic: keywords
Dynamic: requires-dist
Dynamic: requires-python
Dynamic: summary
